{
  "msg1": {
    "time": "5:16 PM",
    "user": "kejkaew",
    "message": "Hello"
  },
  "msg2": {
    "time": "2:18 PM",
    "user": "NineMeow",
    "message": "Sawaddeekub"
  },
  "msg3": {
    "time": "2:18 PM",
    "user": "NineMeow",
    "message": ""
  },
  "msg4": {
    "time": "2:18 PM",
    "user": "NineMeow",
    "message": "Bonraiwa"
  },
  "msg5": {
    "time": "2:18 PM",
    "user": "NineMeow",
    "message": ""
  },
  "msg6": {
    "time": "2:18 PM",
    "user": "NineMeow",
    "message": ""
  },
  "msg7": {
    "time": "2:18 PM",
    "user": "NineMeow",
    "message": ""
  },
  "msg8": {
    "time": "2:18 PM",
    "user": "NineMeow",
    "message": ""
  },
  "msg9": {
    "time": "2:18 PM",
    "user": "NineMeow",
    "message": ""
  },
  "msg10": {
    "time": "2:18 PM",
    "user": "NineMeow",
    "message": ""
  },
  "msg11": {
    "time": "2:18 PM",
    "user": "NineMeow",
    "message": ""
  },
  "msg12": {
    "time": "2:18 PM",
    "user": "NineMeow",
    "message": "1"
  },
  "msg13": {
    "time": "2:18 PM",
    "user": "NineMeow",
    "message": ""
  },
  "msg14": {
    "time": "2:18 PM",
    "user": "NineMeow",
    "message": ""
  },
  "msg15": {
    "time": "2:18 PM",
    "user": "NineMeow",
    "message": "1"
  },
  "msg16": {
    "time": "2:18 PM",
    "user": "NineMeow",
    "message": "1"
  },
  "msg17": {
    "time": "2:18 PM",
    "user": "NineMeow",
    "message": ""
  },
  "msg18": {
    "time": "2:18 PM",
    "user": "NineMeow",
    "message": ""
  },
  "msg19": {
    "time": "2:18 PM",
    "user": "NineMeow",
    "message": ""
  },
  "msg20": {
    "time": "2:18 PM",
    "user": "NineMeow",
    "message": ""
  },
  "msg21": {
    "time": "2:18 PM",
    "user": "NineMeow",
    "message": ""
  },
  "msg22": {
    "time": "2:18 PM",
    "user": "NineMeow",
    "message": ""
  },
  "msg23": {
    "time": "2:18 PM",
    "user": "NineMeow",
    "message": ""
  },
  "msg24": {
    "time": "6:22 PM",
    "user": "dd",
    "message": "dkub"
  },
  "msg25": {
    "time": "6:22 PM",
    "user": "dd",
    "message": "da"
  },
  "msg26": {
    "time": "1:22 PM",
    "user": "ff",
    "message": "sfsf"
  },
  "msg27": {
    "time": "1:22 PM",
    "user": "ff",
    "message": "reesf"
  },
  "msg28": {
    "time": "1:25 PM",
    "user": "ff",
    "message": ""
  },
  "msg29": {
    "time": "1:38 PM",
    "user": "dada",
    "message": "adadad"
  },
  "msg30": {
    "time": "1:42 PM",
    "user": "ffff",
    "message": "czcz"
  },
  "msg31": {
    "time": "3:08 PM",
    "user": "ninemaow",
    "message": "จริงพี"
  },
  "msg32": {
    "time": "3:10 PM",
    "user": "</3",
    "message": "พี่ว่าไงผมว่างั้น"
  }
}